src/__init__.py
src/tasks.py
benchsci_cli-0.1.0.dist-info/LICENSE
benchsci_cli-0.1.0.dist-info/METADATA
benchsci_cli-0.1.0.dist-info/WHEEL
benchsci_cli-0.1.0.dist-info/entry_points.txt
benchsci_cli-0.1.0.dist-info/top_level.txt
benchsci_cli-0.1.0.dist-info/RECORD
