Metadata-Version: 2.1
Name: benchsci-cli
Version: 0.1.0
Summary: BenchSci CLI
Home-page: https://github.com/benchsci/benchsci-cli
Author: Harsh Verma
Author-email: harsh@benchsci.com
License: UNKNOWN
Platform: UNKNOWN
Requires-Python: >=3.6
Requires-Dist: invoke
